Metadata-Version: 2.1
Name: protonbites
Version: 0.1
Summary: Most sane way to store JSON data. Simple, light, strongly-typed and secure. (Probably, overall)
Author-email: AWeirdDev <aweirdscratcher@gmail.com>
Project-URL: Source, https://github.com/AWeirdDev/protonbites
Project-URL: Bug Tracker, https://github.com/AWeirdDev/protonbites/issues
Keywords: protonbites,proton,bytes,encode,decode,json,protobuf,encoder,decoder,schema
Classifier: Programming Language :: Python :: 3
Classifier: License :: OSI Approved :: MIT License
Classifier: Operating System :: OS Independent
Requires-Python: >=3.9
